hvar/__init__.py
hvar/myfunctions.py
tests/__init__.py
tests/test_myfunctions.py
hvar-0.1.0.dist-info/METADATA
hvar-0.1.0.dist-info/WHEEL
hvar-0.1.0.dist-info/top_level.txt
hvar-0.1.0.dist-info/RECORD
